{
  "objectInfo" : {
    "id" : "2giEKucFYg8c3WMKGjiYep",
    "name" : "Taskflow1",
    "type" : "TASKFLOW",
    "metadata" : {
      "modelVersion" : {
        "major" : 1,
        "minor" : 0
      },
      "repoInfo" : {
        "repoHandle" : "xeEaaaaaaaaaaaa-gt-9412573-2022-01-25T21:51:04.337Z::tf.xml"
      },
      "contextAttributes" : null,
      "additionalInfo" : {
        "description" : "",
        "contentType" : "application/json; charset=utf-8",
        "documentState" : "VALID"
      }
    }
  },
  "dataFileExtension" : "xml",
  "objectRefs" : [ {
    "id" : "8XILG8nwlRiiZdBkM3inKn",
    "name" : "MappingTask3",
    "type" : "MTT",
    "metadata" : {
      "modelVersion" : {
        "major" : 0,
        "minor" : 0
      },
      "repoInfo" : {
        "repoHandle" : "01ASU60Z00000000001T"
      },
      "contextAttributes" : [ {
        "name" : "id",
        "value" : "@1"
      } ],
      "additionalInfo" : {
        "description" : "",
        "contentType" : "JSON",
        "documentState" : "VALID"
      }
    },
    "path" : "/Explore/SandBox/04263599"
  }, {
    "id" : "0PGc6arkFWFhZlXV6uYUm6",
    "name" : "MytMappingTask2",
    "type" : "MTT",
    "metadata" : {
      "modelVersion" : {
        "major" : 0,
        "minor" : 0
      },
      "repoInfo" : {
        "repoHandle" : "01ASU60Z00000000001S"
      },
      "contextAttributes" : [ {
        "name" : "id",
        "value" : "@1"
      } ],
      "additionalInfo" : {
        "description" : "",
        "contentType" : "JSON",
        "documentState" : "VALID"
      }
    },
    "path" : "/Explore/SandBox/04263599"
  } ]
}